yjxj_jupyter/__init__.py
yjxj_jupyter/monitor.py
yjxj_jupyter-0.3.0.dist-info/METADATA
yjxj_jupyter-0.3.0.dist-info/WHEEL
yjxj_jupyter-0.3.0.dist-info/top_level.txt
yjxj_jupyter-0.3.0.dist-info/RECORD
