Metadata-Version: 2.1
Name: yjxj_jupyter
Version: 0.3.0
Summary: Jupyter工具包【单个单元格时间与内存消耗】
Author: 鼬君夏纪
Author-email: youjunxiaji@gmail.com
Classifier: Programming Language :: Python :: 3
Classifier: License :: OSI Approved :: MIT License
Classifier: Operating System :: OS Independent
Classifier: Framework :: IPython
Classifier: Framework :: Jupyter
Requires-Python: >=3.6
Requires-Dist: ipython>=7.0.0
Requires-Dist: psutil>=5.0.0
